flask_admin_subview/__init__.py
flask_admin_subview/subview.py
flask_admin_subview/subview_container.py
flask_admin_subview/view.py
flask_admin_subview/static/subview.css
flask_admin_subview/static/subview.js
flask_admin_subview/templates/bootstrap3/admin/model/details_with_subview.html
flask_admin_subview/templates/bootstrap3/admin/subview/actions.html
flask_admin_subview/templates/bootstrap3/admin/subview/list.html
flask_admin_subview/templates/bootstrap3/admin/subview/row_actions.html
Flask_Admin_Subview-0.1.2.dist-info/LICENSE
Flask_Admin_Subview-0.1.2.dist-info/METADATA
Flask_Admin_Subview-0.1.2.dist-info/WHEEL
Flask_Admin_Subview-0.1.2.dist-info/top_level.txt
Flask_Admin_Subview-0.1.2.dist-info/RECORD
