Metadata-Version: 2.1
Name: Flask-Admin-Subview
Version: 0.1.2
Summary: Embedded Flask-Admin list views.
Home-page: https://github.com/artemShelest/flask-admin-subview
Author: Artem Shelest
Author-email: artem.e.shelest@gmail.com
License: MIT
Keywords: flask-admin,list,view,embedded,nested,subview,one-to-many,relation,view relations
Platform: any
Classifier: Development Status :: 4 - Beta
Classifier: Intended Audience :: Developers
Classifier: License :: OSI Approved :: MIT License
Classifier: Topic :: Software Development :: Libraries :: Python Modules
Classifier: Programming Language :: Python
Classifier: Programming Language :: Python :: 2.7
Classifier: Programming Language :: Python :: 3
Classifier: Programming Language :: Python :: 3.4
Classifier: Programming Language :: Python :: 3.5
Classifier: Programming Language :: Python :: 3.6
Classifier: Programming Language :: Python :: 3.7
Requires-Dist: flask
Requires-Dist: flask-admin
Requires-Dist: wtforms
